agentc/__init__.py
agentc/__main__.py
agentc/catalog/__init__.py
agentc/span/__init__.py
agentc-0.2.1a1.dist-info/METADATA
agentc-0.2.1a1.dist-info/WHEEL
agentc-0.2.1a1.dist-info/entry_points.txt
agentc-0.2.1a1.dist-info/RECORD
